[{"__type__":"cc.SpriteFrame","content":{"name":"fire","texture":"57cXn9RPFB3qEmMFbuLn1+","rect":[1,1,29,29],"offset":[-0.5,0.5],"originalSize":[32,32],"capInsets":[0,0,0,0]}},[{"__type__":"cc.Prefab","_name":"roleUp","data":{"__id__":1}},{"__type__":"cc.Node","_name":"roleUp","_children":[{"__id__":2},{"__id__":3}],"_level":1,"_prefab":{"__type__":"cc.PrefabInfo","root":{"__id__":1},"asset":{"__uuid__":"774rwaPLNNHpofD7U7nVtu"},"fileId":"c3pl90GkZPiYIF4w2O7U5L"},"_position":{"__type__":"cc.Vec3","y":-693},"_scale":{"__type__":"cc.Vec3","x":1,"y":1,"z":1},"_zIndex":0},{"__type__":"cc.Node","_name":"New Sprite","_parent":{"__id__":1},"_level":2,"_components":[{"__type__":"cc.Sprite","node":{"__id__":2},"_spriteFrame":{"__uuid__":"99F4y/MvVB2ob8jEq0iWXA"}},{"__type__":"cc.Animation","node":{"__id__":2},"_clips":[{"__uuid__":"efWWfWn8RBCaCr8OtmimBU"}]}],"_prefab":{"__type__":"cc.PrefabInfo","root":{"__id__":1},"asset":{"__uuid__":"774rwaPLNNHpofD7U7nVtu"},"fileId":"3aL28G44NI4ZTZJTopcHaw"},"_contentSize":{"__type__":"cc.Size","width":39,"height":39},"_scale":{"__type__":"cc.Vec3","x":1,"y":1,"z":1},"_zIndex":0},{"__type__":"cc.Node","_name":"New Particle","_parent":{"__id__":1},"_level":2,"_components":[{"__type__":"cc.ParticleSystem","node":{"__id__":3},"_custom":true,"_file":{"__uuid__":"e641uFU5pJQKkk+iiCVD2L"},"_spriteFrame":{"__uuid__":"4bTqOpJT1JMI3Q5AsMNENt"},"duration":0.1,"emissionRate":3000,"life":0.05,"lifeVar":0.5,"_startColor":{"__type__":"cc.Color","r":189,"g":192,"b":190},"_startColorVar":{"__type__":"cc.Color","a":0},"_endColor":{"__type__":"cc.Color","r":236,"g":245,"b":218},"_endColorVar":{"__type__":"cc.Color","a":0},"angle":0,"angleVar":359.9999694824219,"startSize":30.45963,"startSizeVar":5.37,"endSize":3,"endSizeVar":5,"posVar":{"__type__":"cc.Vec2","y":4},"gravity":{"__type__":"cc.Vec2","y":-100},"speed":87.27526092529297,"speedVar":0,"tangentialAccel":0,"radialAccel":-100,"radialAccelVar":100}],"_prefab":{"__type__":"cc.PrefabInfo","root":{"__id__":1},"asset":{"__uuid__":"774rwaPLNNHpofD7U7nVtu"},"fileId":"c0GS4FrCpCIZpKNndQ7FZa"},"_scale":{"__type__":"cc.Vec3","x":1,"y":1,"z":1},"_zIndex":0}],{"__type__":"cc.SpriteFrame","content":{"name":"flasheEffect01","texture":"8fhCb7fDBI0ZAwFiXlgWlm","rect":[106,102,39,39],"offset":[4,-6],"originalSize":[243,231],"capInsets":[0,0,0,0]}}]