[{"__type__":"cc.SpriteFrame","content":{"name":"chest1","texture":"5a8gRe76BOvrRPdCA0CNVN","rect":[1324,1743,84,76],"offset":[-2,-8],"originalSize":[92,92],"capInsets":[0,0,0,0]}},{"__type__":"cc.SpriteFrame","content":{"name":"weed1","texture":"5a8gRe76BOvrRPdCA0CNVN","rect":[1817,1023,92,92],"offset":[0,0],"originalSize":[92,92],"capInsets":[0,0,0,0]}},{"__type__":"cc.SpriteFrame","content":{"name":"bomb","texture":"5a8gRe76BOvrRPdCA0CNVN","rect":[1078,1564,88,76],"offset":[-1,-1],"originalSize":[92,92],"capInsets":[0,0,0,0]}},{"__type__":"cc.SpriteFrame","content":{"name":"wood2","texture":"5a8gRe76BOvrRPdCA0CNVN","rect":[1630,1213,92,82],"offset":[0,0],"originalSize":[92,92],"capInsets":[0,0,0,0]}},{"__type__":"cc.SpriteFrame","content":{"name":"weed2","texture":"5a8gRe76BOvrRPdCA0CNVN","rect":[1631,1035,92,92],"offset":[0,0],"originalSize":[92,92],"capInsets":[0,0,0,0]}},[{"__type__":"cc.Prefab","_name":"level45","data":{"__id__":1}},{"__type__":"cc.Node","_name":"level45","_children":[{"__id__":2},{"__id__":12},{"__id__":21},{"__id__":29}],"_level":1,"_prefab":{"__type__":"cc.PrefabInfo","root":{"__id__":1},"asset":{"__uuid__":"78hjsAu4dPlZDerJDtDeEW"},"fileId":"d26Mz8LUJG5rkMiYYsrSiU"},"_contentSize":{"__type__":"cc.Size","width":736,"height":1136},"_position":{"__type__":"cc.Vec3","x":5},"_scale":{"__type__":"cc.Vec3","x":1,"y":1,"z":1}},{"__type__":"cc.Node","_name":"元素布局","_parent":{"__id__":1},"_children":[{"__id__":3},{"__id__":5},{"__id__":6},{"__id__":7},{"__id__":8},{"__id__":9},{"__id__":10},{"__id__":11}],"_level":3,"_prefab":{"__type__":"cc.PrefabInfo","root":{"__id__":1},"asset":{"__uuid__":"78hjsAu4dPlZDerJDtDeEW"},"fileId":"45JkqB/uRE9aADAEfq+8NJ"},"_scale":{"__type__":"cc.Vec3","x":1,"y":1,"z":1}},{"__type__":"cc.Node","_name":"钻石宝箱","_parent":{"__id__":2},"_children":[{"__id__":4}],"_level":4,"_components":[{"__type__":"cc.Sprite","node":{"__id__":3},"_spriteFrame":{"__uuid__":"18OetqOOBPfaf7FR7z2jCD"}}],"_prefab":{"__type__":"cc.PrefabInfo","root":{"__id__":1},"asset":{"__uuid__":"78hjsAu4dPlZDerJDtDeEW"},"fileId":"7fBfKI/T5HSYwQZ9UNv6tA"},"_contentSize":{"__type__":"cc.Size","width":84,"height":76},"_position":{"__type__":"cc.Vec3","x":-326,"y":-326},"_scale":{"__type__":"cc.Vec3","x":1,"y":1,"z":1}},{"__type__":"cc.Node","_name":"sp","_parent":{"__id__":3},"_level":2,"_components":[{"__type__":"cc.Sprite","node":{"__id__":4},"_spriteFrame":{"__uuid__":"cfqmUyvABAOap5iQuEJmsB"}}],"_prefab":{"__type__":"cc.PrefabInfo","root":{"__id__":1},"asset":{"__uuid__":"78hjsAu4dPlZDerJDtDeEW"},"fileId":"44PjJoKJtHxrrpHZTDdSNn"},"_contentSize":{"__type__":"cc.Size","width":80,"height":80},"_scale":{"__type__":"cc.Vec3","x":0.5,"y":0.5,"z":1}},{"__type__":"cc.Node","_name":"杂草1","_parent":{"__id__":2},"_level":4,"_components":[{"__type__":"cc.Sprite","node":{"__id__":5},"_spriteFrame":{"__uuid__":"38B/6dMwdORZ2mMNxi696D"}}],"_prefab":{"__type__":"cc.PrefabInfo","root":{"__id__":1},"asset":{"__uuid__":"78hjsAu4dPlZDerJDtDeEW"},"fileId":"5akPJbRGJGMZxPsPwS9hmn"},"_contentSize":{"__type__":"cc.Size","width":92,"height":92},"_position":{"__type__":"cc.Vec3","x":-323,"y":-223},"_scale":{"__type__":"cc.Vec3","x":1,"y":1,"z":1}},{"__type__":"cc.Node","_name":"钥匙下","_parent":{"__id__":2},"_level":4,"_components":[{"__type__":"cc.Sprite","node":{"__id__":6},"_spriteFrame":{"__uuid__":"d8Uz/m3Q9EYopPxb8jOoev"}}],"_prefab":{"__type__":"cc.PrefabInfo","root":{"__id__":1},"asset":{"__uuid__":"78hjsAu4dPlZDerJDtDeEW"},"fileId":"ccnfUunNBAyYRTTyO2c9FB"},"_contentSize":{"__type__":"cc.Size","width":90,"height":88},"_position":{"__type__":"cc.Vec3","x":-328,"y":240},"_scale":{"__type__":"cc.Vec3","x":1,"y":1,"z":1}},{"__type__":"cc.Node","_name":"清屏炸弹","_parent":{"__id__":2},"_level":4,"_components":[{"__type__":"cc.Sprite","node":{"__id__":7},"_spriteFrame":{"__uuid__":"39b7qCv/dFZIQ4IbMX/qPm"}}],"_prefab":{"__type__":"cc.PrefabInfo","root":{"__id__":1},"asset":{"__uuid__":"78hjsAu4dPlZDerJDtDeEW"},"fileId":"cac8OfWk1EXYk0OA73JOp+"},"_contentSize":{"__type__":"cc.Size","width":88,"height":76},"_position":{"__type__":"cc.Vec3","x":132,"y":-135},"_scale":{"__type__":"cc.Vec3","x":1,"y":1,"z":1}},{"__type__":"cc.Node","_name":"杂草2","_parent":{"__id__":2},"_level":4,"_components":[{"__type__":"cc.Sprite","node":{"__id__":8},"_spriteFrame":{"__uuid__":"64cIajpXhPcqiaOOOUehtl"}}],"_prefab":{"__type__":"cc.PrefabInfo","root":{"__id__":1},"asset":{"__uuid__":"78hjsAu4dPlZDerJDtDeEW"},"fileId":"c0mDLxOdVDXrVpotmgk2Bb"},"_contentSize":{"__type__":"cc.Size","width":92,"height":92},"_position":{"__type__":"cc.Vec3","x":129,"y":-234},"_scale":{"__type__":"cc.Vec3","x":1,"y":1,"z":1}},{"__type__":"cc.Node","_name":"杂草2","_parent":{"__id__":2},"_level":4,"_components":[{"__type__":"cc.Sprite","node":{"__id__":9},"_spriteFrame":{"__uuid__":"64cIajpXhPcqiaOOOUehtl"}}],"_prefab":{"__type__":"cc.PrefabInfo","root":{"__id__":1},"asset":{"__uuid__":"78hjsAu4dPlZDerJDtDeEW"},"fileId":"6bl8YWFFpKRKjeh2t/+VYF"},"_contentSize":{"__type__":"cc.Size","width":92,"height":92},"_position":{"__type__":"cc.Vec3","x":217,"y":-135},"_scale":{"__type__":"cc.Vec3","x":1,"y":1,"z":1}},{"__type__":"cc.Node","_name":"树桩2","_parent":{"__id__":2},"_level":4,"_components":[{"__type__":"cc.Sprite","node":{"__id__":10},"_spriteFrame":{"__uuid__":"45K6fAF+RKabqOkS3PLNdw"}}],"_prefab":{"__type__":"cc.PrefabInfo","root":{"__id__":1},"asset":{"__uuid__":"78hjsAu4dPlZDerJDtDeEW"},"fileId":"a4HEXEEnlDs7aT4tVLYyG+"},"_contentSize":{"__type__":"cc.Size","width":92,"height":82},"_position":{"__type__":"cc.Vec3","x":41,"y":-135},"_scale":{"__type__":"cc.Vec3","x":1,"y":1,"z":1}},{"__type__":"cc.Node","_name":"树桩2","_parent":{"__id__":2},"_level":4,"_components":[{"__type__":"cc.Sprite","node":{"__id__":11},"_spriteFrame":{"__uuid__":"45K6fAF+RKabqOkS3PLNdw"}}],"_prefab":{"__type__":"cc.PrefabInfo","root":{"__id__":1},"asset":{"__uuid__":"78hjsAu4dPlZDerJDtDeEW"},"fileId":"89EiXFd0hDuKiTB4wv7oWJ"},"_contentSize":{"__type__":"cc.Size","width":92,"height":82},"_position":{"__type__":"cc.Vec3","x":132,"y":-55},"_scale":{"__type__":"cc.Vec3","x":1,"y":1,"z":1}},{"__type__":"cc.Node","_name":"怪物布局","_parent":{"__id__":1},"_children":[{"__id__":13},{"__id__":16}],"_level":3,"_prefab":{"__type__":"cc.PrefabInfo","root":{"__id__":1},"asset":{"__uuid__":"78hjsAu4dPlZDerJDtDeEW"},"fileId":"62493N7cRA2qth1Enq+UVI"},"_position":{"__type__":"cc.Vec3","y":-121},"_scale":{"__type__":"cc.Vec3","x":1,"y":1,"z":1}},{"__type__":"cc.Node","_name":"wave1","_parent":{"__id__":12},"_children":[{"__id__":14}],"_level":4,"_prefab":{"__type__":"cc.PrefabInfo","root":{"__id__":1},"asset":{"__uuid__":"78hjsAu4dPlZDerJDtDeEW"},"fileId":"cdxbnsw9BFbYBb5Yi3ahps"},"_scale":{"__type__":"cc.Vec3","x":1,"y":1,"z":1}},{"__type__":"cc.Node","_name":"BOSS2","_parent":{"__id__":13},"_children":[{"__id__":15}],"_level":5,"_prefab":{"__type__":"cc.PrefabInfo","root":{"__id__":1},"asset":{"__uuid__":"78hjsAu4dPlZDerJDtDeEW"},"fileId":"a6jCHj/plEsrO6b5qqte9o"},"_contentSize":{"__type__":"cc.Size","width":128,"height":92},"_anchorPoint":{"__type__":"cc.Vec2","x":0.5},"_position":{"__type__":"cc.Vec3","x":174,"y":639},"_scale":{"__type__":"cc.Vec3","x":0.8,"y":0.8,"z":1},"groupIndex":8},{"__type__":"cc.Node","_name":"skeleton","_parent":{"__id__":14},"_level":2,"_components":[{"__type__":"sp.Skeleton","node":{"__id__":15},"premultipliedAlpha":false,"_N$skeletonData":{"__uuid__":"1dfsTPbC1HWZioTtmsrwqC"}}],"_prefab":{"__type__":"cc.PrefabInfo","root":{"__id__":1},"asset":{"__uuid__":"78hjsAu4dPlZDerJDtDeEW"},"fileId":"0bg/WMOoRIAYnUd0SEtgN5"},"_contentSize":{"__type__":"cc.Size","width":220.99,"height":179},"_scale":{"__type__":"cc.Vec3","x":1,"y":1,"z":1}},{"__type__":"cc.Node","_name":"wave2","_parent":{"__id__":12},"_children":[{"__id__":17},{"__id__":19}],"_level":4,"_prefab":{"__type__":"cc.PrefabInfo","root":{"__id__":1},"asset":{"__uuid__":"78hjsAu4dPlZDerJDtDeEW"},"fileId":"49qrXrfDVM44Xbbooxqfoz"},"_scale":{"__type__":"cc.Vec3","x":1,"y":1,"z":1}},{"__type__":"cc.Node","_name":"BOSS4","_parent":{"__id__":16},"_children":[{"__id__":18}],"_level":5,"_components":[{"__type__":"cc.CircleCollider","node":{"__id__":17},"_enabled":false,"_offset":{"__type__":"cc.Vec2","y":70},"_radius":60}],"_prefab":{"__type__":"cc.PrefabInfo","root":{"__id__":1},"asset":{"__uuid__":"78hjsAu4dPlZDerJDtDeEW"},"fileId":"19OT48q9ZGorAIA6VZcQA6"},"_contentSize":{"__type__":"cc.Size","width":128,"height":92},"_anchorPoint":{"__type__":"cc.Vec2","x":0.5},"_position":{"__type__":"cc.Vec3","x":927,"y":655},"_scale":{"__type__":"cc.Vec3","x":0.8,"y":0.8,"z":1},"groupIndex":8},{"__type__":"cc.Node","_name":"skeleton","_parent":{"__id__":17},"_level":2,"_components":[{"__type__":"sp.Skeleton","node":{"__id__":18},"premultipliedAlpha":false,"_N$skeletonData":{"__uuid__":"805M5WuMdDnqGQcePKYiiR"}}],"_prefab":{"__type__":"cc.PrefabInfo","root":{"__id__":1},"asset":{"__uuid__":"78hjsAu4dPlZDerJDtDeEW"},"fileId":"67/kO2fthMWZ0SVZISZTyA"},"_contentSize":{"__type__":"cc.Size","width":230.35,"height":151.01},"_scale":{"__type__":"cc.Vec3","x":1,"y":1,"z":1}},{"__type__":"cc.Node","_name":"BOSS3","_parent":{"__id__":16},"_children":[{"__id__":20}],"_level":5,"_prefab":{"__type__":"cc.PrefabInfo","root":{"__id__":1},"asset":{"__uuid__":"78hjsAu4dPlZDerJDtDeEW"},"fileId":"29lkfobWJPw5ZdOUVuNRE7"},"_contentSize":{"__type__":"cc.Size","width":128,"height":92},"_anchorPoint":{"__type__":"cc.Vec2","x":0.5},"_position":{"__type__":"cc.Vec3","x":784,"y":644},"_scale":{"__type__":"cc.Vec3","x":0.8,"y":0.8,"z":1},"groupIndex":8},{"__type__":"cc.Node","_name":"skeleton","_parent":{"__id__":19},"_level":2,"_components":[{"__type__":"sp.Skeleton","node":{"__id__":20},"premultipliedAlpha":false,"_N$skeletonData":{"__uuid__":"5et9cQB9NKMaQLFLLous7w"}}],"_prefab":{"__type__":"cc.PrefabInfo","root":{"__id__":1},"asset":{"__uuid__":"78hjsAu4dPlZDerJDtDeEW"},"fileId":"29ePy0bRlGHaOmuvoym4q0"},"_contentSize":{"__type__":"cc.Size","width":171.01,"height":167.98},"_scale":{"__type__":"cc.Vec3","x":1,"y":1,"z":1}},{"__type__":"cc.Node","_name":"关卡目标","_parent":{"__id__":1},"_children":[{"__id__":22},{"__id__":23},{"__id__":26}],"_level":3,"_prefab":{"__type__":"cc.PrefabInfo","root":{"__id__":1},"asset":{"__uuid__":"78hjsAu4dPlZDerJDtDeEW"},"fileId":"fbzlbFOLVNlbjAR0R9KbvB"},"_position":{"__type__":"cc.Vec3","x":17,"y":554},"_scale":{"__type__":"cc.Vec3","x":1,"y":1,"z":1}},{"__type__":"cc.Node","_name":"步数","_parent":{"__id__":21},"_level":4,"_components":[{"__type__":"cc.Label","node":{"__id__":22},"_srcBlendFactor":1,"_useOriginalSize":false,"_string":"20","_N$string":"20","_fontSize":50,"_lineHeight":50,"_N$file":{"__uuid__":"21j0Fli+tNW7C1IV+8xk86"},"_isSystemFontUsed":false,"_N$horizontalAlign":1,"_N$verticalAlign":1},{"__type__":"cc.LabelOutline","node":{"__id__":22},"_color":{"__type__":"cc.Color","r":97,"g":49,"b":4},"_width":2}],"_prefab":{"__type__":"cc.PrefabInfo","root":{"__id__":1},"asset":{"__uuid__":"78hjsAu4dPlZDerJDtDeEW"},"fileId":"f7O5KSApVFGKwfyTE1wwVC"},"_contentSize":{"__type__":"cc.Size","width":61.1,"height":50},"_position":{"__type__":"cc.Vec3","x":-1044,"y":-1111},"_scale":{"__type__":"cc.Vec3","x":2,"y":2,"z":1}},{"__type__":"cc.Node","_name":"全屏炸弹","_parent":{"__id__":21},"_children":[{"__id__":24},{"__id__":25}],"_level":4,"_prefab":{"__type__":"cc.PrefabInfo","root":{"__id__":1},"asset":{"__uuid__":"78hjsAu4dPlZDerJDtDeEW"},"fileId":"af8r76zWxJxpXyo6zg9K3J"},"_anchorPoint":{"__type__":"cc.Vec2","x":0.5},"_position":{"__type__":"cc.Vec3","x":-1080,"y":-558},"_scale":{"__type__":"cc.Vec3","x":3,"y":3,"z":1}},{"__type__":"cc.Node","_name":"target","_parent":{"__id__":23},"_level":2,"_components":[{"__type__":"cc.Sprite","node":{"__id__":24},"_spriteFrame":{"__uuid__":"39b7qCv/dFZIQ4IbMX/qPm"},"_sizeMode":0}],"_prefab":{"__type__":"cc.PrefabInfo","root":{"__id__":1},"asset":{"__uuid__":"78hjsAu4dPlZDerJDtDeEW"},"fileId":"f4dpI6W4JBgqgvz7MHd61e"},"_contentSize":{"__type__":"cc.Size","width":92,"height":92},"_position":{"__type__":"cc.Vec3","y":2.1},"_scale":{"__type__":"cc.Vec3","x":0.5,"y":0.5,"z":1}},{"__type__":"cc.Node","_name":"num","_parent":{"__id__":23},"_level":6,"_components":[{"__type__":"cc.Label","node":{"__id__":25},"_string":"1","_N$string":"1","_fontSize":20,"_N$file":{"__uuid__":"24pT27GhRPBbopYrHMfQpB"},"_isSystemFontUsed":false}],"_prefab":{"__type__":"cc.PrefabInfo","root":{"__id__":1},"asset":{"__uuid__":"78hjsAu4dPlZDerJDtDeEW"},"fileId":"9bEoKA4ShNoLxdmhPU9jGI"},"_contentSize":{"__type__":"cc.Size","width":18.18,"height":36.36},"_anchorPoint":{"__type__":"cc.Vec2","y":0.5},"_position":{"__type__":"cc.Vec3","x":29,"y":-6},"_scale":{"__type__":"cc.Vec3","x":1,"y":1,"z":1}},{"__type__":"cc.Node","_name":"宝箱","_parent":{"__id__":21},"_children":[{"__id__":27},{"__id__":28}],"_level":4,"_prefab":{"__type__":"cc.PrefabInfo","root":{"__id__":1},"asset":{"__uuid__":"78hjsAu4dPlZDerJDtDeEW"},"fileId":"dfw1VBPNZH04alozD5x0Hi"},"_position":{"__type__":"cc.Vec3","x":-1125,"y":-750},"_scale":{"__type__":"cc.Vec3","x":1,"y":1,"z":1}},{"__type__":"cc.Node","_name":"target","_parent":{"__id__":26},"_level":5,"_components":[{"__type__":"cc.Sprite","node":{"__id__":27},"_spriteFrame":{"__uuid__":"18OetqOOBPfaf7FR7z2jCD"}}],"_prefab":{"__type__":"cc.PrefabInfo","root":{"__id__":1},"asset":{"__uuid__":"78hjsAu4dPlZDerJDtDeEW"},"fileId":"1dzqOb0zhHNohaK5lejpLv"},"_contentSize":{"__type__":"cc.Size","width":84,"height":76},"_position":{"__type__":"cc.Vec3","x":54,"y":14},"_scale":{"__type__":"cc.Vec3","x":2,"y":2,"z":1}},{"__type__":"cc.Node","_name":"num","_parent":{"__id__":26},"_level":5,"_components":[{"__type__":"cc.Label","node":{"__id__":28},"_string":"1","_N$string":"1","_fontSize":59.7,"_N$file":{"__uuid__":"24pT27GhRPBbopYrHMfQpB"},"_isSystemFontUsed":false}],"_prefab":{"__type__":"cc.PrefabInfo","root":{"__id__":1},"asset":{"__uuid__":"78hjsAu4dPlZDerJDtDeEW"},"fileId":"5b2thi3iFPs6ri/afePVMP"},"_contentSize":{"__type__":"cc.Size","width":54.27,"height":108.55},"_anchorPoint":{"__type__":"cc.Vec2","y":0.5},"_position":{"__type__":"cc.Vec3","x":148,"y":1},"_scale":{"__type__":"cc.Vec3","x":1,"y":1,"z":1}},{"__type__":"cc.Node","_name":"下落概率","_parent":{"__id__":1},"_children":[{"__id__":30},{"__id__":33},{"__id__":36},{"__id__":39},{"__id__":42}],"_level":3,"_prefab":{"__type__":"cc.PrefabInfo","root":{"__id__":1},"asset":{"__uuid__":"78hjsAu4dPlZDerJDtDeEW"},"fileId":"b31AFndfZEur2FQr7cPBU7"},"_scale":{"__type__":"cc.Vec3","x":1,"y":1,"z":1}},{"__type__":"cc.Node","_name":"萝卜","_parent":{"__id__":29},"_children":[{"__id__":31},{"__id__":32}],"_level":4,"_prefab":{"__type__":"cc.PrefabInfo","root":{"__id__":1},"asset":{"__uuid__":"78hjsAu4dPlZDerJDtDeEW"},"fileId":"06XQ+RXP1N6pxpXEJ7t8Jq"},"_position":{"__type__":"cc.Vec3","x":325,"y":-1100},"_scale":{"__type__":"cc.Vec3","x":4,"y":4,"z":1}},{"__type__":"cc.Node","_name":"target","_parent":{"__id__":30},"_level":5,"_components":[{"__type__":"sp.Skeleton","node":{"__id__":31},"_N$skeletonData":{"__uuid__":"c8Pnytlu5Fc5hGRCQAoUwM"}}],"_prefab":{"__type__":"cc.PrefabInfo","root":{"__id__":1},"asset":{"__uuid__":"78hjsAu4dPlZDerJDtDeEW"},"fileId":"85ekoC/XtB6Iy+1ud8P/BI"},"_contentSize":{"__type__":"cc.Size","width":78.99,"height":82.99},"_position":{"__type__":"cc.Vec3","y":-6.1},"_scale":{"__type__":"cc.Vec3","x":0.4,"y":0.4,"z":1}},{"__type__":"cc.Node","_name":"num","_parent":{"__id__":30},"_level":5,"_components":[{"__type__":"cc.Label","node":{"__id__":32},"_srcBlendFactor":1,"_useOriginalSize":false,"_string":"100","_N$string":"100","_N$file":{"__uuid__":"21j0Fli+tNW7C1IV+8xk86"},"_isSystemFontUsed":false,"_N$horizontalAlign":1,"_N$verticalAlign":1},{"__type__":"cc.LabelOutline","node":{"__id__":32},"_color":{"__type__":"cc.Color","r":97,"g":49,"b":4},"_width":2}],"_prefab":{"__type__":"cc.PrefabInfo","root":{"__id__":1},"asset":{"__uuid__":"78hjsAu4dPlZDerJDtDeEW"},"fileId":"fbJDka0/VPUJu45ojvN4rV"},"_contentSize":{"__type__":"cc.Size","width":69.84,"height":40},"_anchorPoint":{"__type__":"cc.Vec2","y":0.5},"_position":{"__type__":"cc.Vec3","x":36.3,"y":7.6},"_scale":{"__type__":"cc.Vec3","x":1,"y":1,"z":1}},{"__type__":"cc.Node","_name":"西红柿","_parent":{"__id__":29},"_children":[{"__id__":34},{"__id__":35}],"_level":4,"_components":[{"__type__":"cc.Widget","node":{"__id__":33},"_alignFlags":9,"_left":-565,"_top":849}],"_prefab":{"__type__":"cc.PrefabInfo","root":{"__id__":1},"asset":{"__uuid__":"78hjsAu4dPlZDerJDtDeEW"},"fileId":"17zqdGMN1MoalQrkPdY50P"},"_position":{"__type__":"cc.Vec3","x":-565,"y":-849},"_scale":{"__type__":"cc.Vec3","x":4,"y":4,"z":1}},{"__type__":"cc.Node","_name":"target","_parent":{"__id__":33},"_level":5,"_components":[{"__type__":"sp.Skeleton","node":{"__id__":34},"_N$skeletonData":{"__uuid__":"e9W646ZrhPx6+IG0sZDz53"}}],"_prefab":{"__type__":"cc.PrefabInfo","root":{"__id__":1},"asset":{"__uuid__":"78hjsAu4dPlZDerJDtDeEW"},"fileId":"b6rwbl/wZOwrNPWLNruSya"},"_contentSize":{"__type__":"cc.Size","width":83.03,"height":82.03},"_position":{"__type__":"cc.Vec3","y":-6.1},"_scale":{"__type__":"cc.Vec3","x":0.4,"y":0.4,"z":1}},{"__type__":"cc.Node","_name":"num","_parent":{"__id__":33},"_level":5,"_components":[{"__type__":"cc.Label","node":{"__id__":35},"_srcBlendFactor":1,"_useOriginalSize":false,"_string":"200","_N$string":"200","_N$file":{"__uuid__":"21j0Fli+tNW7C1IV+8xk86"},"_isSystemFontUsed":false,"_N$horizontalAlign":1,"_N$verticalAlign":1},{"__type__":"cc.LabelOutline","node":{"__id__":35},"_color":{"__type__":"cc.Color","r":97,"g":49,"b":4},"_width":2}],"_prefab":{"__type__":"cc.PrefabInfo","root":{"__id__":1},"asset":{"__uuid__":"78hjsAu4dPlZDerJDtDeEW"},"fileId":"0dtWHQLJ5NLrYEdQKryRlr"},"_contentSize":{"__type__":"cc.Size","width":72.4,"height":40},"_anchorPoint":{"__type__":"cc.Vec2","y":0.5},"_position":{"__type__":"cc.Vec3","x":36.3,"y":7.6},"_scale":{"__type__":"cc.Vec3","x":1,"y":1,"z":1}},{"__type__":"cc.Node","_name":"苹果","_parent":{"__id__":29},"_children":[{"__id__":37},{"__id__":38}],"_level":4,"_components":[{"__type__":"cc.Widget","node":{"__id__":36},"_alignFlags":9,"_left":-147,"_top":837}],"_prefab":{"__type__":"cc.PrefabInfo","root":{"__id__":1},"asset":{"__uuid__":"78hjsAu4dPlZDerJDtDeEW"},"fileId":"81ZpBh6MpKYLcnd/Ugmt2X"},"_position":{"__type__":"cc.Vec3","x":-147,"y":-837},"_scale":{"__type__":"cc.Vec3","x":4,"y":4,"z":1}},{"__type__":"cc.Node","_name":"target","_parent":{"__id__":36},"_level":5,"_components":[{"__type__":"sp.Skeleton","node":{"__id__":37},"_N$skeletonData":{"__uuid__":"46//9FHP5KEIBhZSOPt8/p"}}],"_prefab":{"__type__":"cc.PrefabInfo","root":{"__id__":1},"asset":{"__uuid__":"78hjsAu4dPlZDerJDtDeEW"},"fileId":"47J6M/TEtEJp5iKxGAi0zT"},"_contentSize":{"__type__":"cc.Size","width":82.99,"height":82.99},"_position":{"__type__":"cc.Vec3","y":-6.1},"_scale":{"__type__":"cc.Vec3","x":0.4,"y":0.4,"z":1}},{"__type__":"cc.Node","_name":"num","_parent":{"__id__":36},"_level":5,"_components":[{"__type__":"cc.Label","node":{"__id__":38},"_srcBlendFactor":1,"_useOriginalSize":false,"_string":"200","_N$string":"200","_N$file":{"__uuid__":"21j0Fli+tNW7C1IV+8xk86"},"_isSystemFontUsed":false,"_N$horizontalAlign":1,"_N$verticalAlign":1},{"__type__":"cc.LabelOutline","node":{"__id__":38},"_color":{"__type__":"cc.Color","r":97,"g":49,"b":4},"_width":2}],"_prefab":{"__type__":"cc.PrefabInfo","root":{"__id__":1},"asset":{"__uuid__":"78hjsAu4dPlZDerJDtDeEW"},"fileId":"84lJkm4Y5AyIlc1Wjz3Zby"},"_contentSize":{"__type__":"cc.Size","width":72.4,"height":40},"_anchorPoint":{"__type__":"cc.Vec2","y":0.5},"_position":{"__type__":"cc.Vec3","x":36,"y":5},"_scale":{"__type__":"cc.Vec3","x":1,"y":1,"z":1}},{"__type__":"cc.Node","_name":"茄子","_parent":{"__id__":29},"_children":[{"__id__":40},{"__id__":41}],"_level":4,"_prefab":{"__type__":"cc.PrefabInfo","root":{"__id__":1},"asset":{"__uuid__":"78hjsAu4dPlZDerJDtDeEW"},"fileId":"71QFbgbh1IeaPt7213PYIr"},"_position":{"__type__":"cc.Vec3","x":428,"y":-844},"_scale":{"__type__":"cc.Vec3","x":4,"y":4,"z":1}},{"__type__":"cc.Node","_name":"target","_parent":{"__id__":39},"_level":5,"_components":[{"__type__":"sp.Skeleton","node":{"__id__":40},"_N$skeletonData":{"__uuid__":"abzUVCP8NJI5DkYFZErBd1"}}],"_prefab":{"__type__":"cc.PrefabInfo","root":{"__id__":1},"asset":{"__uuid__":"78hjsAu4dPlZDerJDtDeEW"},"fileId":"4auFJs8ExMtYN6jLRoNFL9"},"_contentSize":{"__type__":"cc.Size","width":65.03,"height":85.02},"_position":{"__type__":"cc.Vec3","y":-6.1},"_scale":{"__type__":"cc.Vec3","x":0.4,"y":0.4,"z":1}},{"__type__":"cc.Node","_name":"num","_parent":{"__id__":39},"_level":5,"_components":[{"__type__":"cc.Label","node":{"__id__":41},"_srcBlendFactor":1,"_useOriginalSize":false,"_string":"200","_N$string":"200","_N$file":{"__uuid__":"21j0Fli+tNW7C1IV+8xk86"},"_isSystemFontUsed":false,"_N$horizontalAlign":1,"_N$verticalAlign":1},{"__type__":"cc.LabelOutline","node":{"__id__":41},"_color":{"__type__":"cc.Color","r":97,"g":49,"b":4},"_width":2}],"_prefab":{"__type__":"cc.PrefabInfo","root":{"__id__":1},"asset":{"__uuid__":"78hjsAu4dPlZDerJDtDeEW"},"fileId":"9bemRLaZ9BnIfliqd8I8cb"},"_contentSize":{"__type__":"cc.Size","width":72.4,"height":40},"_anchorPoint":{"__type__":"cc.Vec2","y":0.5},"_position":{"__type__":"cc.Vec3","x":36.3,"y":7.6},"_scale":{"__type__":"cc.Vec3","x":1,"y":1,"z":1}},{"__type__":"cc.Node","_name":"橙子","_parent":{"__id__":29},"_children":[{"__id__":43},{"__id__":44}],"_level":4,"_prefab":{"__type__":"cc.PrefabInfo","root":{"__id__":1},"asset":{"__uuid__":"78hjsAu4dPlZDerJDtDeEW"},"fileId":"61NweglfBLe5+EgjLox4Bq"},"_position":{"__type__":"cc.Vec3","x":-228,"y":-1106},"_scale":{"__type__":"cc.Vec3","x":4,"y":4,"z":1}},{"__type__":"cc.Node","_name":"target","_parent":{"__id__":42},"_level":5,"_components":[{"__type__":"sp.Skeleton","node":{"__id__":43},"_N$skeletonData":{"__uuid__":"8doESLuxZA2rwAf9EV4Mi6"}}],"_prefab":{"__type__":"cc.PrefabInfo","root":{"__id__":1},"asset":{"__uuid__":"78hjsAu4dPlZDerJDtDeEW"},"fileId":"17uDIk6LVK1L+VGIlZsKtc"},"_contentSize":{"__type__":"cc.Size","width":79.99,"height":81.99},"_position":{"__type__":"cc.Vec3","y":-6.1},"_scale":{"__type__":"cc.Vec3","x":0.4,"y":0.4,"z":1}},{"__type__":"cc.Node","_name":"num","_parent":{"__id__":42},"_level":5,"_components":[{"__type__":"cc.Label","node":{"__id__":44},"_srcBlendFactor":1,"_useOriginalSize":false,"_string":"100","_N$string":"100","_N$file":{"__uuid__":"21j0Fli+tNW7C1IV+8xk86"},"_isSystemFontUsed":false,"_N$horizontalAlign":1,"_N$verticalAlign":1},{"__type__":"cc.LabelOutline","node":{"__id__":44},"_color":{"__type__":"cc.Color","r":97,"g":49,"b":4},"_width":2}],"_prefab":{"__type__":"cc.PrefabInfo","root":{"__id__":1},"asset":{"__uuid__":"78hjsAu4dPlZDerJDtDeEW"},"fileId":"96PilIDqlH96ZFeN/W/sWi"},"_contentSize":{"__type__":"cc.Size","width":69.84,"height":40},"_anchorPoint":{"__type__":"cc.Vec2","y":0.5},"_position":{"__type__":"cc.Vec3","x":36.3,"y":7.6},"_scale":{"__type__":"cc.Vec3","x":1,"y":1,"z":1}}],{"__type__":"cc.SpriteFrame","content":{"name":"lotteryDiamond","texture":"5a8gRe76BOvrRPdCA0CNVN","rect":[1821,1377,80,80],"offset":[0,0],"originalSize":[80,80],"capInsets":[0,0,0,0]}},{"__type__":"cc.SpriteFrame","content":{"name":"keydown","texture":"5a8gRe76BOvrRPdCA0CNVN","rect":[1271,1270,90,88],"offset":[1,0],"originalSize":[92,92],"capInsets":[0,0,0,0]}}]